chemeco/__init__.py
chemeco/initialization/__init__.py
chemeco/initialization/data.py
chemeco/initialization/initialization.py
chemeco/notebooks/__init__.py
chemeco/notebooks/main.py
chemeco/notebooks/templates.py
chemeco/notebooks/tutorials.py
chemeco/utils/__init__.py
chemeco/utils/lib_jcode.py
chemeco/utils/utilities.py
chemeco/utils/validation.py
chemeco/wrappers/__init__.py
chemeco/wrappers/base.py
chemeco/wrappers/engine.py
chemeco/wrappers/chemml_cml/__init__.py
chemeco/wrappers/chemml_cml/cheml_wrapper.py
chemeco/wrappers/database/TSHF.py
chemeco/wrappers/database/__init__.py
chemeco/wrappers/database/cheml_db.py
chemeco/wrappers/database/containers.py
chemeco/wrappers/database/extract_params.py
chemeco/wrappers/database/pandas_db.py
chemeco/wrappers/database/parser.py
chemeco/wrappers/database/sklearn_db.py
chemeco/wrappers/database/unhooked/__init__.py
chemeco/wrappers/database/unhooked/sklearn_db.py
chemeco/wrappers/database/unhooked/sklearn_db2.py
chemeco/wrappers/pandas_pd/__init__.py
chemeco/wrappers/pandas_pd/pandas_wrapper.py
chemeco/wrappers/sklearn_skl/__init__.py
chemeco/wrappers/sklearn_skl/sklearn_wrapper.py
chemeco/wrappers/sklearn_skl/syntax.py
chemeco/wrappers/tensorflow_tf/__init__.py
chemeco/wrappers/tensorflow_tf/tf_wrapper.py
chemeco-0.1.0.data/scripts/chemecoshell
chemeco-0.1.0.dist-info/METADATA
chemeco-0.1.0.dist-info/RECORD
chemeco-0.1.0.dist-info/WHEEL
chemeco-0.1.0.dist-info/top_level.txt
