Metadata-Version: 2.1
Name: chemeco
Version: 0.1.0
Summary: A General-Purpose Framework for Data Mining Without Coding
Home-page: UNKNOWN
Author: Mojtaba Haghighatlari, Johannes Hachmann
Author-email: mojtabah@buffalo.edu, hachmann@buffalo.edu
License: BSD-3C
Project-URL: url, https://hachmannlab.github.io/chemeco/
Project-URL: Source, https://github.com/hachmannlab/chemeco
Platform: UNKNOWN
Classifier: Development Status :: 4 - Beta
Classifier: Intended Audience :: Science/Research
Classifier: Programming Language :: Python :: 3.5
Classifier: Programming Language :: Python :: 3.6
Provides-Extra: docs
Provides-Extra: tests
Requires-Dist: future
Requires-Dist: six
Requires-Dist: numpy
Requires-Dist: pandas
Requires-Dist: graphviz
Requires-Dist: ipywidgets
Requires-Dist: widgetsnbextension
Requires-Dist: chemml
Requires-Dist: scikit-learn
Provides-Extra: docs
Requires-Dist: sphinx; extra == 'docs'
Requires-Dist: sphinxcontrib-napoleon; extra == 'docs'
Requires-Dist: sphinx-rtd-theme; extra == 'docs'
Requires-Dist: numpydoc; extra == 'docs'
Provides-Extra: tests
Requires-Dist: pytest; extra == 'tests'
Requires-Dist: pytest-cov; extra == 'tests'
Requires-Dist: pytest-pep8; extra == 'tests'
Requires-Dist: tox; extra == 'tests'
